bestai/__init__.py
bestai/client.py
bestai/router.py
bestai/utils.py
bestai/examples/simple_router.py
bestai-0.1.0.dist-info/METADATA
bestai-0.1.0.dist-info/WHEEL
bestai-0.1.0.dist-info/top_level.txt
bestai-0.1.0.dist-info/RECORD
